dronebuddylib/__init__.py
dronebuddylib/atoms/__init__.py
dronebuddylib/atoms/bodyfeatureextraction/__init__.py
dronebuddylib/atoms/bodyfeatureextraction/body_feature_extraction_impl.py
dronebuddylib/atoms/bodyfeatureextraction/hand_feature_extraction_impl.py
dronebuddylib/atoms/bodyfeatureextraction/head_feature_extraction_impl.py
dronebuddylib/atoms/bodyfeatureextraction/i_feature_extraction.py
dronebuddylib/atoms/bodyfeatureextraction/resources/GestureRecognizerResult.py
dronebuddylib/atoms/bodyfeatureextraction/resources/gestures.py
dronebuddylib/atoms/facerecognition/__init__.py
dronebuddylib/atoms/facerecognition/face_recognition_deepface_impl.py
dronebuddylib/atoms/facerecognition/face_recognition_engine.py
dronebuddylib/atoms/facerecognition/face_recognition_euclidean_impl.py
dronebuddylib/atoms/facerecognition/face_recognition_knn_impl.py
dronebuddylib/atoms/facerecognition/face_recognition_result.py
dronebuddylib/atoms/facerecognition/i_face_recognition.py
dronebuddylib/atoms/facerecognition/resources/known_names.txt
dronebuddylib/atoms/facerecognition/resources/images/John.jpg
dronebuddylib/atoms/facerecognition/resources/images/test_file
dronebuddylib/atoms/facerecognition/resources/test_data/testing_data/README.md
dronebuddylib/atoms/facerecognition/resources/test_data/training_data/README.md
dronebuddylib/atoms/facerecognition/resources/test_data/validation_data/README.md
dronebuddylib/atoms/intentrecognition/__init__.py
dronebuddylib/atoms/intentrecognition/gpt_intent_recognition_impl.py
dronebuddylib/atoms/intentrecognition/i_intent_recognition.py
dronebuddylib/atoms/intentrecognition/intent_recognition_engine.py
dronebuddylib/atoms/intentrecognition/recognized_intent_result.py
dronebuddylib/atoms/intentrecognition/snips_intent_recognition_impl.py
dronebuddylib/atoms/intentrecognition/resources/intents.txt
dronebuddylib/atoms/intentrecognition/resources/intentrecognition/dataset.json
dronebuddylib-2.1.0.dist-info/METADATA
dronebuddylib-2.1.0.dist-info/WHEEL
dronebuddylib-2.1.0.dist-info/top_level.txt
dronebuddylib-2.1.0.dist-info/RECORD
