Metadata-Version: 2.4
Name: dronebuddylib
Version: 2.1.0
Summary: Everything to control and customize Tello
Author: NUS
Author-email: malshadz@nus.edu.sg
License: MIT
Requires-Python: >=3.9
Requires-Dist: requests~=2.28.0
Requires-Dist: numpy~=1.23.0
Requires-Dist: cython~=0.29.34
Requires-Dist: setuptools~=69.2.0
Requires-Dist: packaging~=23.0
Requires-Dist: pyparsing~=3.0.9
Requires-Dist: tensorflow~=2.16.1
Requires-Dist: opencv-python~=4.7.0.72
Requires-Dist: mediapipe~=0.10.9
Requires-Dist: pyttsx3~=2.90
Requires-Dist: djitellopy~=2.5.0
Requires-Dist: torch==2.3.0+cu121
Requires-Dist: PyAudio~=0.2.13
Requires-Dist: google~=3.0.0
Requires-Dist: socketio~=0.2.1
Requires-Dist: SpeechRecognition~=3.10.1
Requires-Dist: openai~=1.30.1
Requires-Dist: joblib~=1.3.2
Requires-Dist: scikit-learn~=0.22.2.post1
Requires-Dist: tqdm~=4.66.1
Requires-Dist: ultralytics~=8.2.2
Requires-Dist: torchvision~=0.18.0
Requires-Dist: pillow~=10.3.0
Requires-Dist: vosk~=0.3.45
Requires-Dist: pandas~=2.1.1
Requires-Dist: matplotlib~=3.7.2
Requires-Dist: keras~=3.1.1
Requires-Dist: tabulate~=0.9.0
Requires-Dist: seaborn~=0.13.0
Requires-Dist: boto3~=1.34.107
Requires-Dist: botocore~=1.34.107
Requires-Dist: tiktoken~=0.5.1
Requires-Dist: langchain~=0.3.26
Requires-Dist: langgraph~=0.5.1
Provides-Extra: face-recognition
Requires-Dist: face-recognition; extra == "face-recognition"
Provides-Extra: intent-recognition-gpt
Requires-Dist: openai; extra == "intent-recognition-gpt"
Requires-Dist: tiktoken; extra == "intent-recognition-gpt"
Provides-Extra: intent-recognition-snips
Requires-Dist: snips-nlu; extra == "intent-recognition-snips"
Provides-Extra: object-detection-mp
Requires-Dist: mediapipe; extra == "object-detection-mp"
Provides-Extra: object-detection-yolo
Requires-Dist: ultralytics; extra == "object-detection-yolo"
Provides-Extra: text-recognition
Requires-Dist: google-cloud-vision; extra == "text-recognition"
Provides-Extra: speech-recognition-multi
Requires-Dist: SpeechRecognition; extra == "speech-recognition-multi"
Provides-Extra: speech-recognition-vosk
Requires-Dist: vosk; extra == "speech-recognition-vosk"
Provides-Extra: speech-recognition-google
Requires-Dist: google-cloud-speech; extra == "speech-recognition-google"
Provides-Extra: speech-generation
Requires-Dist: pyttsx3; extra == "speech-generation"
Provides-Extra: object-identification
Requires-Dist: openai; extra == "object-identification"
Requires-Dist: tiktoken; extra == "object-identification"
Provides-Extra: llm-integration
Requires-Dist: openai; extra == "llm-integration"
Requires-Dist: tiktoken; extra == "llm-integration"
Provides-Extra: place-recognition
Requires-Dist: scikit-learn; extra == "place-recognition"
Requires-Dist: numpy; extra == "place-recognition"
Requires-Dist: torch; extra == "place-recognition"
Requires-Dist: torchvision; extra == "place-recognition"
Requires-Dist: Pillow; extra == "place-recognition"
Requires-Dist: tqdm; extra == "place-recognition"
Requires-Dist: opencv-python; extra == "place-recognition"
Provides-Extra: navigation-tello
Requires-Dist: djitellopy; extra == "navigation-tello"
Dynamic: author
Dynamic: author-email
Dynamic: description
Dynamic: description-content-type
Dynamic: license
Dynamic: provides-extra
Dynamic: requires-dist
Dynamic: requires-python
Dynamic: summary
